ovllm/__init__.py
ovllm-0.3.0.dist-info/licenses/LICENSE
ovllm-0.3.0.dist-info/METADATA
ovllm-0.3.0.dist-info/WHEEL
ovllm-0.3.0.dist-info/top_level.txt
ovllm-0.3.0.dist-info/RECORD
