Metadata-Version: 2.4
Name: ovllm
Version: 0.3.0
Summary: One-line vLLM wrapper with gorgeous DSPy integration
Author-email: Maxime Rivest <mrive052@gmail.com>
License: MIT
Project-URL: Homepage, https://github.com/maximerivest/ovllm
Project-URL: Documentation, https://ovllm.readthedocs.io
Project-URL: Repository, https://github.com/maximerivest/ovllm
Project-URL: Issues, https://github.com/maximerivest/ovllm/issues
Keywords: llm,vllm,dspy,ai,machine-learning,deep-learning,language-models
Classifier: Development Status :: 4 - Beta
Classifier: Intended Audience :: Developers
Classifier: Intended Audience :: Science/Research
Classifier: License :: OSI Approved :: MIT License
Classifier: Operating System :: OS Independent
Classifier: Programming Language :: Python :: 3
Classifier: Programming Language :: Python :: 3.10
Classifier: Programming Language :: Python :: 3.11
Classifier: Programming Language :: Python :: 3.12
Classifier: Topic :: Scientific/Engineering :: Artificial Intelligence
Requires-Python: <3.13,>=3.10
License-File: LICENSE
Requires-Dist: vllm>=0.10.0
Requires-Dist: torch>=2.0.0
Requires-Dist: transformers>=4.30.0
Requires-Dist: dspy>=3.0.0b3
Provides-Extra: dev
Requires-Dist: pytest>=7.0.0; extra == "dev"
Requires-Dist: pytest-asyncio>=0.21.0; extra == "dev"
Requires-Dist: black>=23.0.0; extra == "dev"
Requires-Dist: ruff>=0.1.0; extra == "dev"
Requires-Dist: mypy>=1.0.0; extra == "dev"
Provides-Extra: docs
Requires-Dist: sphinx>=5.0.0; extra == "docs"
Requires-Dist: sphinx-rtd-theme>=1.2.0; extra == "docs"
Requires-Dist: sphinx-autodoc-typehints>=1.22.0; extra == "docs"
Dynamic: license-file
